topsis/__init__.py
topsis/topsis.py
Topsis_Jasmine_102217225-1.0.0.dist-info/LICENSE
Topsis_Jasmine_102217225-1.0.0.dist-info/METADATA
Topsis_Jasmine_102217225-1.0.0.dist-info/WHEEL
Topsis_Jasmine_102217225-1.0.0.dist-info/entry_points.txt
Topsis_Jasmine_102217225-1.0.0.dist-info/top_level.txt
Topsis_Jasmine_102217225-1.0.0.dist-info/RECORD
